README.md
setup.cfg
setup.py
fae/__init__.py
fae/decode.py
fae/evaluate.py
fae/metrics.py
fae/utils.py
fae.egg-info/PKG-INFO
fae.egg-info/SOURCES.txt
fae.egg-info/dependency_links.txt
fae.egg-info/entry_points.txt
fae.egg-info/not-zip-safe
fae.egg-info/requires.txt
fae.egg-info/top_level.txt
fae/resources/500WordsSortedList.txt
fae/resources/emotions8.pth
fae/resources/lrw.pth
fae/resources/mean_face.npy