Metadata-Version: 1.1
Name: fae
Version: 0.1
Summary: Facial animation evaluation suite
Home-page: https://github.com/DinoMan/facial-animation-evaluation.git
Author: Dino Vougioukas
Author-email: dinovgk@gmail.com
License: MIT
Download-URL: https://github.com/DinoMan/facial-animation-evaluation/archive/refs/tags/v0.1.tar.gz
Platform: UNKNOWN
